repixelator/__init__.py
repixelator/cmd.py
repixelator/icon.ico
repixelator/repixelator.py
repixelator/repixelator_gui.py
repixelator-1.0.1.dist-info/LICENSE.txt
repixelator-1.0.1.dist-info/METADATA
repixelator-1.0.1.dist-info/WHEEL
repixelator-1.0.1.dist-info/entry_points.txt
repixelator-1.0.1.dist-info/top_level.txt
repixelator-1.0.1.dist-info/RECORD
