Metadata-Version: 2.1
Name: repixelator
Version: 1.0.1
Summary: Converts resized pixel arts to their original resolution
Home-page: https://github.com/yclee126/RePixelator
Author: YeongChan Lee
Author-email: yclee126@gmail.com
License: MIT License
Platform: UNKNOWN
Classifier: Programming Language :: Python :: 3
Classifier: License :: OSI Approved :: MIT License
Classifier: Operating System :: OS Independent
Requires-Python: >=3.5
License-File: LICENSE.txt
Requires-Dist: opencv-python
Requires-Dist: numpy
